celery_results_rest/__init__.py
celery_results_rest/filters.py
celery_results_rest/serializers.py
celery_results_rest/urls.py
celery_results_rest/views.py
django_celery_results_rest-0.0.4.dist-info/LICENSE
django_celery_results_rest-0.0.4.dist-info/METADATA
django_celery_results_rest-0.0.4.dist-info/WHEEL
django_celery_results_rest-0.0.4.dist-info/top_level.txt
django_celery_results_rest-0.0.4.dist-info/RECORD
